wikidictparser/__init__.py
wikidictparser/base.py
wikidictparser/english.py
wikidictparser/polish.py
wikidictparser/router.py
wikidictparser-1.4.dist-info/LICENSE
wikidictparser-1.4.dist-info/METADATA
wikidictparser-1.4.dist-info/WHEEL
wikidictparser-1.4.dist-info/top_level.txt
wikidictparser-1.4.dist-info/RECORD
