Metadata-Version: 2.1
Name: wikidictparser
Version: 1.4
Summary: Wikidict parser package
Home-page: https://github.com/ls2716/wikidictparser_package
Author: Lukasz Sliwinski
Author-email: luki3141@gmail.com
License: Copyright (c) 2020, Lukasz Sliwinski
Requires-Dist: requests
Requires-Dist: bs4
Requires-Dist: pandas
Requires-Dist: lxml
